matrix_validator/__init__.py
matrix_validator/checks/__init__.py
matrix_validator/checks/check_column_contains_biolink_model_agent_type.py
matrix_validator/checks/check_column_contains_biolink_model_knowledge_level.py
matrix_validator/checks/check_column_contains_biolink_model_prefix.py
matrix_validator/checks/check_column_enum.py
matrix_validator/checks/check_column_is_delimited_by_pipes.py
matrix_validator/checks/check_column_is_valid_curie.py
matrix_validator/checks/check_column_no_leading_whitespace.py
matrix_validator/checks/check_column_no_trailing_whitespace.py
matrix_validator/checks/check_column_range.py
matrix_validator/checks/check_column_starts_with_biolink.py
matrix_validator/checks/check_edge_ids_in_node_ids.py
matrix_validator/checks/check_node_id_and_category_with_biolink_preferred_prefixes.py
matrix_validator/cli.py
matrix_validator/datamodels.py
matrix_validator/util.py
matrix_validator/validator.py
matrix_validator/validator_polars.py
matrix_validator/validator_purepython.py
matrix_validator/validator_schema.py
matrix_validator-0.0.6.dist-info/LICENSE
matrix_validator-0.0.6.dist-info/METADATA
matrix_validator-0.0.6.dist-info/WHEEL
matrix_validator-0.0.6.dist-info/entry_points.txt
matrix_validator-0.0.6.dist-info/RECORD
