Metadata-Version: 2.3
Name: matrix-validator
Version: 0.0.6
Summary: matrix-validator
License: BSD-3
Author: Nicolas Matentzoglu
Author-email: nico@semanticly.org
Requires-Python: >=3.11,<4.0
Classifier: License :: Other/Proprietary License
Classifier: Programming Language :: Python :: 3
Classifier: Programming Language :: Python :: 3.11
Classifier: Programming Language :: Python :: 3.12
Classifier: Programming Language :: Python :: 3.13
Requires-Dist: biolink-model (==4.2.6rc4)
Requires-Dist: click
Requires-Dist: importlib-metadata (>=8.2.0)
Requires-Dist: matrix-schema (>=0.2.0,<0.3.0)
Requires-Dist: pandas (>=2.3,<3.0)
Requires-Dist: pandera (>=0.24,<0.25)
Requires-Dist: patito (==0.8.3)
Requires-Dist: polars-lts-cpu (>=1.23.0,<2.0.0)
Requires-Dist: tqdm
